setup.py
changuito/__init__.py
changuito/middleware.py
changuito/models.py
changuito/proxy.py
changuito/signals.py
changuito/views.py
django_changuito.egg-info/PKG-INFO
django_changuito.egg-info/SOURCES.txt
django_changuito.egg-info/dependency_links.txt
django_changuito.egg-info/top_level.txt