Metadata-Version: 1.1
Name: django-changuito
Version: 1.1
Summary: A fork of django-cart with the same simplicity but updated
Home-page: https://github.com/angvp/django-changuito
Author: Angel Velasquez
Author-email: angvp@archlinux.org
License: LGPL v3
Platform: UNKNOWN
Classifier: Development Status :: 5 - Production/Stable
Classifier: Environment :: Web Environment
Classifier: Framework :: Django
Classifier: Intended Audience :: Developers
Classifier: Operating System :: OS Independent
Classifier: Programming Language :: Python
Classifier: Topic :: Software Development :: Libraries :: Python Modules
